buem/__init__.py
buem/main.py
buem/config/__init__.py
buem/config/cfg_attribute.py
buem/data/__init__.py
buem/thermal/__init__.py
buem/thermal/model_buem.py
buem-0.1.1.dist-info/licenses/LICENSE
buem-0.1.1.dist-info/METADATA
buem-0.1.1.dist-info/WHEEL
buem-0.1.1.dist-info/entry_points.txt
buem-0.1.1.dist-info/top_level.txt
buem-0.1.1.dist-info/RECORD
