Metadata-Version: 2.4
Name: buem
Version: 0.1.1
Summary: Building energy model for analysis of hourly thermal load(ISO 52019-1:2017, 5R1C)
Author-email: Somadutta Sahoo <s.sahoo@uu.nl>
License: MIT License
Keywords: building,energy-model,energy-communities,parameterization,open-source,heating-cooling,python
Classifier: Programming Language :: Python :: 3
Classifier: License :: OSI Approved :: MIT License
Classifier: Operating System :: OS Independent
Classifier: Intended Audience :: Science/Research
Classifier: Topic :: Scientific/Engineering :: GIS
Requires-Python: >=3.11
License-File: LICENSE
Requires-Dist: matplotlib
Requires-Dist: numpy
Requires-Dist: pandas
Requires-Dist: pvlib
Requires-Dist: scipy
Requires-Dist: sympy
Requires-Dist: openpyxl
Requires-Dist: cvxpy
Dynamic: license-file
